{
    "title": "{title}",
    "Sections": [
        {
            "index": 1,
            "Section": "第一章 {keyword}市场概述",
            "child": [
                {
                    "index": 1,
                    "Section": "第一节 {keyword}行业定义"
                },
                {
                    "index": 2,
                    "Section": "第二节 {keyword}行业发展历程"
                },
                {
                    "index": 3,
                    "Section": "第三节 {keyword}市场特点分析"
                },
                {
                    "index": 4,
                    "Section": "第四节 {keyword}行业发展周期特征分析"
                }
            ]
        },
        {
            "index": 2,
            "Section": "第二章 {keyword}行业环境分析",
            "child": [
                {
                    "index": 1,
                    "Section": "第一节 经济发展环境分析"
                },
                {
                    "index": 2,
                    "Section": "第二节 {keyword}行业政策环境分析"
                },
                {
                    "index": 3,
                    "Section": "第三节 {keyword}行业技术环境分析"
                }
            ]
        },
        {
            "index": 3,
            "Section": "第三章 {keyword}行业国内外市场发展分析",
            "child": [
                {
                    "index": 1,
                    "Section": "第一节 {keyword}行业国际市场分析"
                },
                {
                    "index": 2,
                    "Section": "第二节 {keyword}行业国内市场分析"
                },
                {
                    "index": 3,
                    "Section": "第三节 {keyword}行业未来发展预测分析"
                }
            ]
        },
        {
            "index": 4,
            "Section": "第四章 {keyword}行业各地区产销率数据分析",
            "child": [
                {
                    "index": 1,
                    "Section": "第一节 {keyword}行业产销率调查"
                },
                {
                    "index": 2,
                    "Section": "第二节 华北地区{keyword}行业产销率调查"
                },
                {
                    "index": 3,
                    "Section": "第三节 东北地区{keyword}行业产销率调查"
                },
                {
                    "index": 4,
                    "Section": "第四节 西北地区{keyword}行业产销率调查"
                },
                {
                    "index": 5,
                    "Section": "第五节 华东地区{keyword}行业产销率调查"
                },
                {
                    "index": 6,
                    "Section": "第六节 中南地区{keyword}行业产销率调查"
                },
                {
                    "index": 7,
                    "Section": "第七节 西南地区{keyword}行业产销率调查"
                }
            ]
        },
        {
            "index": 5,
            "Section": "第五章 {keyword}行业进出口分析",
            "child": [
                {
                    "index": 1,
                    "Section": "第一节 {keyword}出口状况分析"
                },
                {
                    "index": 2,
                    "Section": "第二节 {keyword}进口状况"
                }
            ]
        },
        {
            "index": 6,
            "Section": "第六章 {keyword}市场竞争分析",
            "child": [
                {
                    "index": 1,
                    "Section": "第一节 {keyword}发展现状分析"
                },
                {
                    "index": 2,
                    "Section": "第二节 {keyword}市场竞争现状分析"
                },
                {
                    "index": 3,
                    "Section": "第三节 {keyword}行业发展驱动因素分析"
                }
            ]
        },
        {
            "index": 7,
            "Section": "第七章 {keyword}产业渠道分析",
            "child": [
                {
                    "index": 1,
                    "Section": "第一节 {area}{keyword}产品的经销模式"
                },
                {
                    "index": 2,
                    "Section": "第二节 {keyword}行业国际化营销模式分析"
                },
                {
                    "index": 3,
                    "Section": "第三节 {area}{keyword}产品生产及销售投资运作模式分析"
                }
            ]
        },
        {
            "index": 8,
            "Section": "第八章 {keyword}行业相关产业分析",
            "child": [
                {
                    "index": 1,
                    "Section": "第一节 {keyword}行业产业链概述"
                },
                {
                    "index": 2,
                    "Section": "第二节 {keyword}行业上游运行分析"
                },
                {
                    "index": 3,
                    "Section": "第三节 {keyword}行业下游运行分析"
                }
            ]
        },
        {
            "index": 9,
            "Section": "第九章 {keyword}行业发展前景预测分析",
            "child": [
                {
                    "index": 1,
                    "Section": "第一节 {keyword}产品发展趋势预测分析"
                },
                {
                    "index": 2,
                    "Section": "第二节 {keyword}行业市场发展前景预测分析"
                },
                {
                    "index": 3,
                    "Section": "第三节 {keyword}行业市场盈利能力预测分析"
                }
            ]
        },
        {
            "index": 10,
            "Section": "第十章 {keyword}产业投资机会与风险研究",
            "child": [
                {
                    "index": 1,
                    "Section": "第一节 {keyword}产业投资机会分析"
                },
                {
                    "index": 2,
                    "Section": "第二节 {keyword}产业投资风险分析"
                },
                {
                    "index": 3,
                    "Section": "第三节 专家建议"
                }
            ]
        }
    ]
}